CTUtil/__init__.py
CTUtil/util.py
CTUtil/Parse/Filed.py
CTUtil/Parse/__init__.py
CTUtil/Response/__init__.py
CTUtil/Response/response.py
CTUtil/email/__init__.py
CTUtil/email/util.py
CTUtil/middleware/__init__.py
CTUtil/middleware/exception.py
CTUtil/models/BaseModels.py
CTUtil/models/__init__.py
CTUtil/types/__init__.py
CTUtil/views/Base.py
CTUtil/views/__init__.py
CTUtil-0.0.2.dist-info/DESCRIPTION.rst
CTUtil-0.0.2.dist-info/METADATA
CTUtil-0.0.2.dist-info/RECORD
CTUtil-0.0.2.dist-info/WHEEL
CTUtil-0.0.2.dist-info/metadata.json
CTUtil-0.0.2.dist-info/top_level.txt
