Metadata-Version: 2.0
Name: CTUtil
Version: 0.0.2
Summary: cingta django web util
Home-page: https://github.com/JiaYingZhang/CTUtil
Author: kaka zhang
Author-email: zhangjiaying121@163.com
License: MIT Licence
Keywords: pip,pathtool,timetool,magetool,mage
Platform: any
Classifier: Programming Language :: Python :: 3
Classifier: License :: OSI Approved :: MIT License
Classifier: Operating System :: OS Independent
Requires-Python: >=3
Requires-Dist: itsdangerous
Requires-Dist: django
